ssmd/__init__.py
ssmd/_version.py
ssmd/capabilities.py
ssmd/document.py
ssmd/formatter.py
ssmd/paragraph.py
ssmd/parser.py
ssmd/parser_types.py
ssmd/py.typed
ssmd/segment.py
ssmd/sentence.py
ssmd/spans.py
ssmd/ssml_conversions.py
ssmd/ssml_parser.py
ssmd/types.py
ssmd/utils.py
ssmd/xsampa_to_ipa.txt
ssmd/data/amazon-alexa.json
ssmd/data/amazon-polly.json
ssmd/data/blank.json
ssmd/data/google-home.json
ssmd/data/ibm-watson.json
ssmd/data/microsoft-azure.json
ssmd/data/microsoft-cortana.json
ssmd-0.7.2.dist-info/licenses/LICENSE
ssmd-0.7.2.dist-info/METADATA
ssmd-0.7.2.dist-info/WHEEL
ssmd-0.7.2.dist-info/top_level.txt
ssmd-0.7.2.dist-info/RECORD
